manage_fields/__init__.py
manage_fields/mixins.py
manage_fields-0.0.7.dist-info/METADATA
manage_fields-0.0.7.dist-info/WHEEL
manage_fields-0.0.7.dist-info/top_level.txt
manage_fields-0.0.7.dist-info/RECORD
