Metadata-Version: 2.1
Name: manage-fields
Version: 0.0.7
Summary: Manage fields by request params
Author: Maxmudov Asliddin
Author-email: <asliddin750750@gmail.com>
Keywords: python,field,serializer,manage fields
Classifier: Development Status :: 1 - Planning
Classifier: Intended Audience :: Developers
Classifier: Programming Language :: Python :: 3
Classifier: Operating System :: Unix
Classifier: Operating System :: MacOS :: MacOS X
Classifier: Operating System :: Microsoft :: Windows
Requires-Dist: Django
Requires-Dist: djangorestframework
